README.txt
setup.py
cursive/__init__.py
cursive.pymag.egg-info/PKG-INFO
cursive.pymag.egg-info/SOURCES.txt
cursive.pymag.egg-info/dependency_links.txt
cursive.pymag.egg-info/entry_points.txt
cursive.pymag.egg-info/namespace_packages.txt
cursive.pymag.egg-info/not-zip-safe
cursive.pymag.egg-info/requires.txt
cursive.pymag.egg-info/top_level.txt
cursive/pymag/__init__.py
cursive/pymag/format.py