Metadata-Version: 1.0
Name: cursive.pymag
Version: 0.1
Summary: Author tools for Python Magazine
Home-page: UNKNOWN
Author: Brandon Craig Rhodes
Author-email: brandon@rhodesmill.org
License: UNKNOWN
Platform: UNKNOWN
